event_synchronization
